{
  "parent": "minecraft:recipes/root",
  "rewards": {
    "recipes": [
      "lavaplus:crate"
    ]
  },
  "criteria": {
    "stick": {
      "trigger": "minecraft:inventory_changed",
      "conditions": {
        "items": [
          {
            "items": [
              "minecraft:stick"
            ]
          }
        ]
      }
    },
    "has_the_recipe": {
      "trigger": "minecraft:recipe_unlocked",
      "conditions": {
        "recipe": "lavaplus:crate"
      }
    }
  },
  "requirements": [
    [
      "stick",
      "has_the_recipe"
    ]
  ]
}